MANIFEST.in
setup.py
docs/CONTRIBUTORS.txt
docs/HISTORY.txt
docs/LICENSE.ZPL
docs/LICENSE.txt
docs/README.txt
src/ztfy/__init__.py
src/ztfy.imgtags.egg-info/PKG-INFO
src/ztfy.imgtags.egg-info/SOURCES.txt
src/ztfy.imgtags.egg-info/dependency_links.txt
src/ztfy.imgtags.egg-info/entry_points.txt
src/ztfy.imgtags.egg-info/namespace_packages.txt
src/ztfy.imgtags.egg-info/not-zip-safe
src/ztfy.imgtags.egg-info/requires.txt
src/ztfy.imgtags.egg-info/top_level.txt
src/ztfy/imgtags/__init__.py
src/ztfy/imgtags/adapter.py
src/ztfy/imgtags/configure.zcml
src/ztfy/imgtags/interfaces.py
src/ztfy/imgtags/browser/__init__.py
src/ztfy/imgtags/browser/configure.zcml
src/ztfy/imgtags/browser/tags.pt
src/ztfy/imgtags/browser/test.py
src/ztfy/imgtags/browser/test.zcml
src/ztfy/imgtags/doctests/README.txt
src/ztfy/imgtags/locales/ztfy.imgtags.pot
src/ztfy/imgtags/locales/en/LC_MESSAGES/ztfy.imgtags.po
src/ztfy/imgtags/tests/__init__.py
src/ztfy/imgtags/tests/test_docs.py
src/ztfy/imgtags/tests/test_docstrings.py