Metadata-Version: 1.1
Name: ztfy.imgtags
Version: 0.1.1
Summary: ZTFY package for EXIF/IPTC/XMP tags management
Home-page: http://hg.ztfy.org/ztfy.imgtags
Author: Thierry Florac
Author-email: tflorac@ulthar.net
License: zpl
Keywords: ZTFY EXIF IPTC XMP
Platform: UNKNOWN
Classifier: Programming Language :: Python
